food_proportion-0.1.0.dist-info/METADATA
food_proportion-0.1.0.dist-info/WHEEL
food_proportion/__init__.py
food_proportion-0.1.0.dist-info/RECORD
