Metadata-Version: 2.1
Name: food-proportion
Version: 0.1.0
Summary: Let me tell you the proportion of food
Author-Email: junsungs950 <junsungs950@gmail.com>
License: MIT
Requires-Python: >=3.9
